{"cameraMode":{"drawMode":2,"name":"Shaded Wireframe","section":"Shading Mode"},"sceneLighting":true,"audioPlay":false,"sceneViewState":{"m_AlwaysRefresh":false,"showFog":true,"showSkybox":true,"showFlares":true,"showImageEffects":true,"showParticleSystems":true,"showVisualEffectGraphs":true,"m_FxEnabled":false},"in2DMode":false,"pivot":{"x":-206.25567626953126,"y":-256.6605224609375,"z":244.50332641601563},"rotation":{"x":0.33869796991348269,"y":-0.4088318645954132,"z":0.16654391586780549,"w":0.8309320211410523},"size":291.2755126953125,"orthographic":false}